Metadata-Version: 2.1
Name: appstartup
Version: 2.0.3
Summary: My short description for my project.
Home-page: https://github.com/me/myproject
Author: Awesome Soul
Author-email: me@example.com
License: MIT
Classifier: License :: OSI Approved :: MIT License
Classifier: Programming Language :: Python
Classifier: Programming Language :: Python :: 3
Classifier: Programming Language :: Python :: 3.6
Classifier: Programming Language :: Python :: Implementation :: CPython
Classifier: Programming Language :: Python :: Implementation :: PyPy
Requires-Python: >=3.6.0
License-File: LICENSE
